{
  "project_info": {
    "project_number": "406502198414",
    "project_id": "cartrackingapp-1575d",
    "storage_bucket": "cartrackingapp-1575d.appspot.com"
  },
  "client": [
    {
      "client_info": {
        "mobilesdk_app_id": "1:406502198414:android:a6ad0fe7c1d06188ed0ddf",
        "android_client_info": {
          "package_name": "at.wifi.swdev.cartrackingapp"
        }
      },
      "oauth_client": [
        {
          "client_id": "406502198414-mgl5rbov5b2kh4g6dno56acs2rsuk4pe.apps.googleusercontent.com",
          "client_type": 3
        }
      ],
      "api_key": [
        {
          "current_key": "AIzaSyD4NvIFVdwdIMKcj1mwIrtlqyg82DxtypU"
        }
      ],
      "services": {
        "appinvite_service": {
          "other_platform_oauth_client": [
            {
              "client_id": "406502198414-mgl5rbov5b2kh4g6dno56acs2rsuk4pe.apps.googleusercontent.com",
              "client_type": 3
            }
          ]
        }
      }
    }
  ],
  "configuration_version": "1"
}